<annotation>
	<folder>images-train</folder>
	<filename>75.jpg</filename>
	<path>/Users/caijieying/docs/AI/floorDetection/dataset2/images-train/75.jpg</path>
	<source>
		<database>Unknown</database>
	</source>
	<size>
		<width>658</width>
		<height>7623</height>
		<depth>3</depth>
	</size>
	<segmented>0</segmented>
	<object>
		<name>toutu</name>
		<pose>Unspecified</pose>
		<truncated>1</truncated>
		<difficult>0</difficult>
		<bndbox>
			<xmin>1</xmin>
			<ymin>104</ymin>
			<xmax>658</xmax>
			<ymax>478</ymax>
		</bndbox>
	</object>
	<object>
		<name>floors</name>
		<pose>Unspecified</pose>
		<truncated>1</truncated>
		<difficult>0</difficult>
		<bndbox>
			<xmin>1</xmin>
			<ymin>487</ymin>
			<xmax>658</xmax>
			<ymax>979</ymax>
		</bndbox>
	</object>
	<object>
		<name>floors</name>
		<pose>Unspecified</pose>
		<truncated>1</truncated>
		<difficult>0</difficult>
		<bndbox>
			<xmin>1</xmin>
			<ymin>987</ymin>
			<xmax>658</xmax>
			<ymax>1185</ymax>
		</bndbox>
	</object>
	<object>
		<name>floors</name>
		<pose>Unspecified</pose>
		<truncated>1</truncated>
		<difficult>0</difficult>
		<bndbox>
			<xmin>1</xmin>
			<ymin>1209</ymin>
			<xmax>658</xmax>
			<ymax>4552</ymax>
		</bndbox>
	</object>
	<object>
		<name>floors</name>
		<pose>Unspecified</pose>
		<truncated>1</truncated>
		<difficult>0</difficult>
		<bndbox>
			<xmin>1</xmin>
			<ymin>4567</ymin>
			<xmax>658</xmax>
			<ymax>5160</ymax>
		</bndbox>
	</object>
	<object>
		<name>floors</name>
		<pose>Unspecified</pose>
		<truncated>1</truncated>
		<difficult>0</difficult>
		<bndbox>
			<xmin>1</xmin>
			<ymin>5185</ymin>
			<xmax>658</xmax>
			<ymax>6070</ymax>
		</bndbox>
	</object>
	<object>
		<name>floors</name>
		<pose>Unspecified</pose>
		<truncated>1</truncated>
		<difficult>0</difficult>
		<bndbox>
			<xmin>1</xmin>
			<ymin>6087</ymin>
			<xmax>658</xmax>
			<ymax>6597</ymax>
		</bndbox>
	</object>
	<object>
		<name>floors</name>
		<pose>Unspecified</pose>
		<truncated>1</truncated>
		<difficult>0</difficult>
		<bndbox>
			<xmin>1</xmin>
			<ymin>6617</ymin>
			<xmax>658</xmax>
			<ymax>7534</ymax>
		</bndbox>
	</object>
</annotation>
